MANIFEST.in
README.rst
setup.py
fanova/__init__.py
fanova/__version__.py
fanova/fanova.py
fanova/visualizer.py
fanova.egg-info/PKG-INFO
fanova.egg-info/SOURCES.txt
fanova.egg-info/dependency_links.txt
fanova.egg-info/requires.txt
fanova.egg-info/top_level.txt