Metadata-Version: 1.0
Name: fanova
Version: 2.0.13
Summary: Functional ANOVA: an implementation of the ICML 2014 paper 'An Efficient Approach for Assessing Hyperparameter Importance' by Frank Hutter, Holger Hoos and Kevin Leyton-Brown.
Home-page: http://automl.org/fanova
Author: Stefan Falkner and Christina Hernandez Wunsch. Legacy branch: Tobias Domhan, Aaron Klein and Frank Hutter (FANOVA)
Author-email: sfalkner@cs.uni-freiburg.de
License: FANOVA is free for academic & non-commercial usage. Please contact Frank Hutter(fh@informatik.uni-freiburg.de) to discuss obtaining a license for commercial purposes.
Keywords: hyperparameter parameter optimization bayesian smac global variance analysis
Platform: UNKNOWN
